security_util/__init__.py
tests/__init__.py
security_util-0.0.4.dist-info/METADATA
security_util-0.0.4.dist-info/WHEEL
security_util-0.0.4.dist-info/top_level.txt
security_util-0.0.4.dist-info/zip-safe
security_util-0.0.4.dist-info/RECORD
