Metadata-Version: 2.1
Name: security-util
Version: 0.0.4
Summary: Security util for python
Author: Battle Furry <btlfry@gmail.com>
Author-email: btlfry@gmail.com
License: MIT
Keywords: security
